{"api":{"results":29,"leagues":[{"league_id":4,"name":"Ligue 1","country":"France","country_code":"FR","season":2018,"season_start":"2018-08-10","season_end":"2019-05-24","logo":"https:\/\/www.api-football.com\/public\/leagues\/4.svg","flag":"https:\/\/www.api-football.com\/public\/flags\/fr.svg","standings":1,"is_current":0},{"league_id":5,"name":"Ligue 2","country":"France","country_code":"FR","season":2018,"season_start":"2018-07-27","season_end":"2019-05-17","logo":"https:\/\/www.api-football.com\/public\/leagues\/5.png","flag":"https:\/\/www.api-football.com\/public\/flags\/fr.svg","standings":1,"is_current":0},{"league_id":22,"name":"Ligue 1","country":"France","country_code":"FR","season":2017,"season_start":"2017-08-04","season_end":"2018-05-19","logo":"https:\/\/www.api-football.com\/public\/leagues\/22.svg","flag":"https:\/\/www.api-football.com\/public\/flags\/fr.svg","standings":1,"is_current":0},{"league_id":23,"name":"Ligue 1","country":"France","country_code":"FR","season":2016,"season_start":"2016-08-12","season_end":"2017-05-20","logo":"https:\/\/www.api-football.com\/public\/leagues\/23.svg","flag":"https:\/\/www.api-football.com\/public\/flags\/fr.svg","standings":1,"is_current":0},{"league_id":24,"name":"Ligue 2","country":"France","country_code":"FR","season":2017,"season_start":"2017-07-28","season_end":"2018-05-20","logo":"https:\/\/www.api-football.com\/public\/leagues\/24.png","flag":"https:\/\/www.api-football.com\/public\/flags\/fr.svg","standings":1,"is_current":0},{"league_id":25,"name":"Ligue 2","country":"France","country_code":"FR","season":2016,"season_start":"2016-07-29","season_end":"2017-05-19","logo":"https:\/\/www.api-football.com\/public\/leagues\/25.png","flag":"https:\/\/www.api-football.com\/public\/flags\/fr.svg","standings":1,"is_current":0},{"league_id":156,"name":"National","country":"France","country_code":"FR","season":2018,"season_start":"2018-08-03","season_end":"2019-05-17","logo":"https:\/\/www.api-football.com\/public\/leagues\/156.png","flag":"https:\/\/www.api-football.com\/public\/flags\/fr.svg","standings":1,"is_current":0},{"league_id":157,"name":"National","country":"France","country_code":"FR","season":2017,"season_start":"2017-08-04","season_end":"2018-05-11","logo":"https:\/\/www.api-football.com\/public\/leagues\/157.png","flag":"https:\/\/www.api-football.com\/public\/flags\/fr.svg","standings":1,"is_current":0},{"league_id":158,"name":"National","country":"France","country_code":"FR","season":2016,"season_start":"2016-08-05","season_end":"2017-05-19","logo":"https:\/\/www.api-football.com\/public\/leagues\/158.png","flag":"https:\/\/www.api-football.com\/public\/flags\/fr.svg","standings":1,"is_current":0},{"league_id":205,"name":"Feminine Division 1","country":"France","country_code":"FR","season":2016,"season_start":"2016-09-10","season_end":"2017-05-25","logo":"https:\/\/www.api-football.com\/public\/leagues\/205.png","flag":"https:\/\/www.api-football.com\/public\/flags\/fr.svg","standings":1,"is_current":0},{"league_id":206,"name":"Feminine Division 1","country":"France","country_code":"FR","season":2017,"season_start":"2017-09-03","season_end":"2018-05-27","logo":"https:\/\/www.api-football.com\/public\/leagues\/206.png","flag":"https:\/\/www.api-football.com\/public\/flags\/fr.svg","standings":1,"is_current":0},{"league_id":207,"name":"Feminine Division 1","country":"France","country_code":"FR","season":2018,"season_start":"2018-08-25","season_end":"2019-05-04","logo":"https:\/\/www.api-football.com\/public\/leagues\/207.png","flag":"https:\/\/www.api-football.com\/public\/flags\/fr.svg","standings":1,"is_current":0},{"league_id":433,"name":"Coupe de la Ligue","country":"France","country_code":"FR","season":2018,"season_start":"2018-08-14","season_end":"2019-03-30","logo":null,"flag":"https:\/\/www.api-football.com\/public\/flags\/fr.svg","standings":0,"is_current":0},{"league_id":434,"name":"Coupe de la Ligue","country":"France","country_code":"FR","season":2017,"season_start":"2017-08-08","season_end":"2018-03-31","logo":null,"flag":"https:\/\/www.api-football.com\/public\/flags\/fr.svg","standings":0,"is_current":0},{"league_id":435,"name":"Coupe de la Ligue","country":"France","country_code":"FR","season":2016,"season_start":"2016-08-09","season_end":"2017-04-01","logo":null,"flag":"https:\/\/www.api-football.com\/public\/flags\/fr.svg","standings":0,"is_current":0},{"league_id":436,"name":"Coupe de France","country":"France","country_code":"FR","season":2018,"season_start":"2018-11-16","season_end":"2019-04-27","logo":null,"flag":"https:\/\/www.api-football.com\/public\/flags\/fr.svg","standings":0,"is_current":1},{"league_id":437,"name":"Coupe de France","country":"France","country_code":"FR","season":2017,"season_start":"2017-11-10","season_end":"2018-05-08","logo":null,"flag":"https:\/\/www.api-football.com\/public\/flags\/fr.svg","standings":0,"is_current":0},{"league_id":438,"name":"Coupe de France","country":"France","country_code":"FR","season":2016,"season_start":"2016-11-11","season_end":"2017-05-27","logo":null,"flag":"https:\/\/www.api-football.com\/public\/flags\/fr.svg","standings":0,"is_current":0},{"league_id":525,"name":"Ligue 1","country":"France","country_code":"FR","season":2019,"season_start":"2019-08-09","season_end":"2020-05-22","logo":"https:\/\/www.api-football.com\/public\/leagues\/4.svg","flag":"https:\/\/www.api-football.com\/public\/flags\/fr.svg","standings":1,"is_current":1},{"league_id":526,"name":"Ligue 2","country":"France","country_code":"FR","season":2019,"season_start":"2019-07-26","season_end":"2020-05-14","logo":"https:\/\/www.api-football.com\/public\/leagues\/5.png","flag":"https:\/\/www.api-football.com\/public\/flags\/fr.svg","standings":1,"is_current":1},{"league_id":677,"name":"Ligue 1","country":"France","country_code":"FR","season":2015,"season_start":"2015-08-07","season_end":"2016-05-14","logo":"https:\/\/www.api-football.com\/public\/leagues\/23.svg","flag":"https:\/\/www.api-football.com\/public\/flags\/fr.svg","standings":1,"is_current":0},{"league_id":678,"name":"Ligue 1","country":"France","country_code":"FR","season":2014,"season_start":"2014-08-08","season_end":"2015-05-23","logo":"https:\/\/www.api-football.com\/public\/leagues\/23.svg","flag":"https:\/\/www.api-football.com\/public\/flags\/fr.svg","standings":1,"is_current":0},{"league_id":679,"name":"Ligue 1","country":"France","country_code":"FR","season":2013,"season_start":"2013-08-09","season_end":"2014-05-17","logo":"https:\/\/www.api-football.com\/public\/leagues\/23.svg","flag":"https:\/\/www.api-football.com\/public\/flags\/fr.svg","standings":1,"is_current":0},{"league_id":680,"name":"Ligue 1","country":"France","country_code":"FR","season":2012,"season_start":"2012-08-10","season_end":"2013-05-26","logo":"https:\/\/www.api-football.com\/public\/leagues\/23.svg","flag":"https:\/\/www.api-football.com\/public\/flags\/fr.svg","standings":1,"is_current":0},{"league_id":681,"name":"Ligue 1","country":"France","country_code":"FR","season":2011,"season_start":"2011-08-06","season_end":"2012-05-20","logo":"https:\/\/www.api-football.com\/public\/leagues\/23.svg","flag":"https:\/\/www.api-football.com\/public\/flags\/fr.svg","standings":1,"is_current":0},{"league_id":682,"name":"Ligue 1","country":"France","country_code":"FR","season":2010,"season_start":"2010-08-07","season_end":"2011-05-29","logo":"https:\/\/www.api-football.com\/public\/leagues\/23.svg","flag":"https:\/\/www.api-football.com\/public\/flags\/fr.svg","standings":1,"is_current":0},{"league_id":762,"name":"National","country":"France","country_code":"FR","season":2019,"season_start":"2019-08-02","season_end":"2020-05-14","logo":"https:\/\/www.api-football.com\/public\/leagues\/156.png","flag":"https:\/\/www.api-football.com\/public\/flags\/fr.svg","standings":1,"is_current":1},{"league_id":783,"name":"Coupe de la Ligue","country":"France","country_code":"FR","season":2019,"season_start":"2019-08-13","season_end":"2019-08-13","logo":null,"flag":"https:\/\/www.api-football.com\/public\/flags\/fr.svg","standings":0,"is_current":1},{"league_id":788,"name":"Feminine Division 1","country":"France","country_code":"FR","season":2019,"season_start":"2019-08-23","season_end":"2020-05-29","logo":"https:\/\/www.api-football.com\/public\/leagues\/207.png","flag":"https:\/\/www.api-football.com\/public\/flags\/fr.svg","standings":1,"is_current":1}]}}